key_manager-0.1.10.dist-info/METADATA
key_manager-0.1.10.dist-info/WHEEL
key_manager-0.1.10.dist-info/licenses/LICENSE
key_manager/__init__.py
key_manager/__pycache__/__init__.cpython-311.pyc
key_manager/key_manager.pyi
key_manager/key_manager.cpython-311-aarch64-linux-gnu.so
key_manager-0.1.10.dist-info/RECORD
