Metadata-Version: 2.4
Name: key-manager
Version: 0.1.10
Classifier: Programming Language :: Python :: 3
Classifier: Programming Language :: Rust
Classifier: License :: OSI Approved :: MIT License
Classifier: Operating System :: OS Independent
License-File: LICENSE
Summary: A Python-wrapped Rust library for RSA JWT generation and validation
Author: Malaa Technologies <engineeering@malaa.tech>
Author-email: Malaa Technologies <engineering@malaa.tech>
License: MIT
